{"BaseModel.d4bdd857-698e-4721-921a-56937e987c08": {"id": "d4bdd857-698e-4721-921a-56937e987c08", "created_at": "2023-07-12T17:03:50.331758", "updated_at": "2023-07-13T15:40:02.234842", "name": "My_First_Model", "my_number": 89, "email": "siya@gmail.com", "__class__": "BaseModel"}, "BaseModel.67c2cacd-a4f7-40ab-a001-d0d1eff080c2": {"id": "67c2cacd-a4f7-40ab-a001-d0d1eff080c2", "created_at": "2023-07-12T17:56:45.044374", "updated_at": "2023-07-12T17:56:45.044374", "name": "My_First_Model", "my_number": 89, "__class__": "BaseModel"}, "BaseModel.0e5e3553-5ce2-473b-9126-69b83a792be0": {"id": "0e5e3553-5ce2-473b-9126-69b83a792be0", "created_at": "2023-07-12T17:58:17.039381", "updated_at": "2023-07-12T17:58:17.040383", "name": "My_First_Model", "my_number": 89, "__class__": "BaseModel"}, "BaseModel.e9965c7e-433f-47fa-8705-567b92adb586": {"id": "e9965c7e-433f-47fa-8705-567b92adb586", "created_at": "2023-07-12T20:32:06.777571", "updated_at": "2023-07-12T20:32:06.777571", "__class__": "BaseModel"}}